pylib/__init__.py
pylib/log.py
pylib/methods.py
pylib/reg_util.py
pylib_test-0.0.1.dist-info/licenses/LICENSE
pylib_test-0.0.1.dist-info/METADATA
pylib_test-0.0.1.dist-info/WHEEL
pylib_test-0.0.1.dist-info/top_level.txt
pylib_test-0.0.1.dist-info/RECORD
