Metadata-Version: 2.4
Name: pylib-test
Version: 0.0.1
Summary: py utils lib
Author-email: Jacob Jiang <jacobjiangmj@gmail.com>
License-Expression: Apache-2.0
Project-URL: Homepage, https://github.com/jacobjiangmj/pylib
Project-URL: Issues, https://github.com/jacobjiangmj/pylib/issues
Classifier: Programming Language :: Python :: 3
Classifier: Operating System :: OS Independent
Requires-Python: >=3.9
License-File: LICENSE
Dynamic: license-file
